graphrelax/__init__.py
graphrelax/_version.py
graphrelax/chain_gaps.py
graphrelax/cli.py
graphrelax/config.py
graphrelax/designer.py
graphrelax/idealize.py
graphrelax/pipeline.py
graphrelax/relaxer.py
graphrelax/resfile.py
graphrelax/structure_io.py
graphrelax/utils.py
graphrelax/weights.py
graphrelax/LigandMPNN/__init__.py
graphrelax/LigandMPNN/data_utils.py
graphrelax/LigandMPNN/model_utils.py
graphrelax/LigandMPNN/sc_utils.py
graphrelax/LigandMPNN/openfold/__init__.py
graphrelax/LigandMPNN/openfold/config.py
graphrelax/LigandMPNN/openfold/data/__init__.py
graphrelax/LigandMPNN/openfold/data/data_transforms.py
graphrelax/LigandMPNN/openfold/np/__init__.py
graphrelax/LigandMPNN/openfold/np/protein.py
graphrelax/LigandMPNN/openfold/np/residue_constants.py
graphrelax/LigandMPNN/openfold/np/relax/__init__.py
graphrelax/LigandMPNN/openfold/np/relax/amber_minimize.py
graphrelax/LigandMPNN/openfold/np/relax/cleanup.py
graphrelax/LigandMPNN/openfold/np/relax/relax.py
graphrelax/LigandMPNN/openfold/np/relax/utils.py
graphrelax/LigandMPNN/openfold/resources/__init__.py
graphrelax/LigandMPNN/openfold/resources/stereo_chemical_props.txt
graphrelax/LigandMPNN/openfold/utils/__init__.py
graphrelax/LigandMPNN/openfold/utils/feats.py
graphrelax/LigandMPNN/openfold/utils/loss.py
graphrelax/LigandMPNN/openfold/utils/rigid_utils.py
graphrelax/LigandMPNN/openfold/utils/tensor_utils.py
graphrelax-0.1.2.dist-info/licenses/LICENSE
graphrelax-0.1.2.dist-info/METADATA
graphrelax-0.1.2.dist-info/WHEEL
graphrelax-0.1.2.dist-info/entry_points.txt
graphrelax-0.1.2.dist-info/top_level.txt
graphrelax-0.1.2.dist-info/RECORD
