Metadata-Version: 2.4
Name: graphrelax
Version: 0.1.2
Summary: Combine LigandMPNN sequence design with AMBER relaxation
Author: GraphRelax Authors
License: MIT
Project-URL: Homepage, https://github.com/delalamo/GraphRelax
Project-URL: Repository, https://github.com/delalamo/GraphRelax
Project-URL: Issues, https://github.com/delalamo/GraphRelax/issues
Keywords: protein,design,relaxation,LigandMPNN,OpenMM,molecular-dynamics,protein-design,bioinformatics
Classifier: Development Status :: 3 - Alpha
Classifier: Intended Audience :: Science/Research
Classifier: Topic :: Scientific/Engineering :: Bio-Informatics
Classifier: License :: OSI Approved :: MIT License
Classifier: Programming Language :: Python :: 3
Classifier: Programming Language :: Python :: 3.9
Classifier: Programming Language :: Python :: 3.10
Classifier: Programming Language :: Python :: 3.11
Requires-Python: >=3.9
License-File: LICENSE
Requires-Dist: torch>=2.0
Requires-Dist: numpy<2
Requires-Dist: prody
Requires-Dist: biopython
Requires-Dist: absl-py
Requires-Dist: ml-collections
Requires-Dist: dm-tree
Requires-Dist: openmm
Provides-Extra: cpu
Requires-Dist: openmm[cpu]; extra == "cpu"
Provides-Extra: cuda11
Requires-Dist: openmm[cuda11]; extra == "cuda11"
Provides-Extra: cuda12
Requires-Dist: openmm[cuda12]; extra == "cuda12"
Provides-Extra: dev
Requires-Dist: pytest; extra == "dev"
Requires-Dist: pytest-cov; extra == "dev"
Provides-Extra: test
Requires-Dist: pytest>=7.0; extra == "test"
Requires-Dist: pytest-cov>=4.1; extra == "test"
Dynamic: license-file
